lucidaflow/__init__.py
lucidaflow/__main__.py
lucidaflow/cli.py
lucidaflow/lucida_analyzer.py
lucidaflow/lucida_ast.py
lucidaflow/lucida_errors.py
lucidaflow/lucida_interpreter.py
lucidaflow/lucida_lexer.py
lucidaflow/lucida_parser.py
lucidaflow/lucida_stdlib.py
lucidaflow/lucida_symbols.py
lucidaflow/lib/__init__.py
lucidaflow/lib/dado.py
lucidaflow/lib/json.py
lucidaflow/lib/math.py
lucidaflow/lib/media.py
lucidaflow/lib/parser_patch.py
lucidaflow/lib/web.py
lucidaflow-1.2.3.dist-info/licenses/LICENSE
lucidaflow-1.2.3.dist-info/METADATA
lucidaflow-1.2.3.dist-info/WHEEL
lucidaflow-1.2.3.dist-info/entry_points.txt
lucidaflow-1.2.3.dist-info/top_level.txt
lucidaflow-1.2.3.dist-info/RECORD
