Metadata-Version: 2.4
Name: lucidaflow
Version: 1.2.3
Summary: Uma linguagem de script moderna, extensível e com tipagem gradual, implementada em Python.
Author-email: Marco Lago <marconeed2@gmail.com>
Project-URL: Homepage, https://github.com/marconeed/Lucida-Flow
Project-URL: Issues, https://github.com/marconeed/Lucida-Flow/issues
Classifier: Programming Language :: Python :: 3
Classifier: License :: OSI Approved :: MIT License
Classifier: Operating System :: OS Independent
Classifier: Topic :: Software Development :: Interpreters
Classifier: Topic :: Software Development :: Compilers
Requires-Python: >=3.9
License-File: LICENSE
Requires-Dist: numpy
Requires-Dist: pysine
Requires-Dist: requests
Dynamic: license-file
